specgenerator/__init__.py
specgenerator/math.py
specgenerator-0.0.3.dist-info/METADATA
specgenerator-0.0.3.dist-info/WHEEL
specgenerator-0.0.3.dist-info/top_level.txt
specgenerator-0.0.3.dist-info/RECORD
